components/__init__.py
components/test1/__init__.py
xander/__init__.py
xander/client/__init__.py
xander/client/client.py
xander/client/routes.py
xander/connectors/__init__.py
xander/connectors/oracle/__init__.py
xander/connectors/oracle/database.py
xander/engine/__init__.py
xander/engine/base.py
xander/engine/ml_component.py
xander/engine/ml_pipeline.py
xander/engine/pipeline.py
xander/engine/simple_component.py
xander/engine/standard_functions.py
xander/engine/storage_manager.py
xander/engine/xander.py
xander/utils/__init__.py
xander/utils/client_utils.py
xander/utils/constants.py
xander/utils/utility.py
xander-0.6.4.dist-info/LICENSE
xander-0.6.4.dist-info/METADATA
xander-0.6.4.dist-info/WHEEL
xander-0.6.4.dist-info/top_level.txt
xander-0.6.4.dist-info/RECORD
