Metadata-Version: 2.1
Name: xander
Version: 0.6.4
Summary: A small ML-ops tool for dummies and anyone who needs it.
Home-page: UNKNOWN
Author: Andrea Cola
Author-email: andrea.cola95@gmail.com
License: UNKNOWN
Platform: UNKNOWN
Classifier: Programming Language :: Python :: 3
Classifier: License :: OSI Approved :: MIT License
Classifier: Operating System :: OS Independent
Requires-Python: >=3.6
License-File: LICENSE
